var hurston = {
 "type": "FeatureCollection",
 "crs": { "type": "name", "properties": { "name": "urn:ogc:def:crs:OGC:1.3:CRS84" } },
 "features": [
 {"type": "Feature", "properties": { "id": 1, "descrip": "hurston" }, "geometry": { "type": "Point", "coordinates": [-79.050230, 35.911202] } }
 ]
 }